pylovepdf/__init__.py
pylovepdf/file.py
pylovepdf/ilovepdf.py
pylovepdf/request.py
pylovepdf/response.py
pylovepdf/task.py
pylovepdf/samples/compress.py
pylovepdf/samples/compress_alternative.py
pylovepdf/samples/imagetopdf.py
pylovepdf/samples/merge.py
pylovepdf/samples/officepdf.py
pylovepdf/samples/pagenumber.py
pylovepdf/samples/pdfa.py
pylovepdf/samples/pdftojpg.py
pylovepdf/samples/protect.py
pylovepdf/samples/rotate.py
pylovepdf/samples/split.py
pylovepdf/samples/unlock.py
pylovepdf/samples/validatepdfa.py
pylovepdf/samples/watermark.py
pylovepdf/tools/__init__.py
pylovepdf/tools/compress.py
pylovepdf/tools/imagetopdf.py
pylovepdf/tools/merge.py
pylovepdf/tools/officepdf.py
pylovepdf/tools/pagenumber.py
pylovepdf/tools/pdfa.py
pylovepdf/tools/pdftojpg.py
pylovepdf/tools/protect.py
pylovepdf/tools/rotate.py
pylovepdf/tools/split.py
pylovepdf/tools/unlock.py
pylovepdf/tools/validatepdfa.py
pylovepdf/tools/watermark.py
pylovepdf-1.3.2.dist-info/LICENSE.md
pylovepdf-1.3.2.dist-info/METADATA
pylovepdf-1.3.2.dist-info/WHEEL
pylovepdf-1.3.2.dist-info/top_level.txt
pylovepdf-1.3.2.dist-info/RECORD
