Metadata-Version: 1.1
Name: pylovepdf
Version: 1.3.2
Summary: ilovepdf.com python API library
Home-page: https://github.com/AndyBTuttofare/pylovepdf
Author: Andrea Bruschi
Author-email: moonx2006@gmail.com
License: GNU GPLv3
Keywords: pdf unlock compress manipulate edit protect pdftojpg jpgtopdf pdfa
Platform: UNKNOWN
Classifier: Development Status :: 5 - Production/Stable
Classifier: License :: OSI Approved :: GNU General Public License v3 (GPLv3)
Classifier: Programming Language :: Python :: 3.6
Classifier: Topic :: Software Development :: Libraries :: Python Modules
